{"title": "Dataflow - \u4f7f\u7528 Apache Beam \u69cb\u5efa\u6d41\u6c34\u7dda", "url": "https://cloud.google.com/dataflow/docs/guides/use-beam?hl=zh-cn", "abstract": "# Dataflow - \u4f7f\u7528 Apache Beam \u69cb\u5efa\u6d41\u6c34\u7dda\nDataflow \u57fa\u65bc\u958b\u6e90 [Apache Beam](https://beam.apache.org/) \u9805\u76ee\u69cb\u5efa\u3002\u60a8\u53ef\u4ee5\u4f7f\u7528 Apache Beam SDK \u7232 Dataflow \u69cb\u5efa\u6d41\u6c34\u7dda\u3002\u672c\u6587\u6a94\u5217\u51fa\u4e86\u4e00\u4e9b Apache Beam \u7de8\u7a0b\u5165\u9580\u7684\u8cc7\u6e90\u3002\n- [\u5b89\u88dd Apache Beam SDK](https://cloud.google.com/dataflow/docs/guides/installing-beam-sdk?hl=zh-cn) \uff1a\u4ecb\u7d39\u5982\u4f55\u5b89\u88dd Apache Beam SDK\uff0c\u4ee5\u4fbf\u5728 Dataflow \u670d\u52d9\u4e0a\u904b\u884c\u6d41\u6c34\u7dda\u3002\n- [Apache Beam \u7de8\u7a0b\u6307\u5357](https://beam.apache.org/documentation/programming-guide/) \uff1a\u63d0\u4f9b\u6709\u95dc\u4f7f\u7528 Apache Beam SDK \u985e\u69cb\u5efa\u548c\u6e2c\u8a66\u6d41\u6c34\u7dda\u7684\u6307\u5c0e\u3002\n- [Apache Beam \u5c0e\u89bd](https://tour.beam.apache.org/) \uff1a\u53ef\u7528\u65bc\u719f\u6089 Apache Beam \u7684\u5b78\u7fd2\u6307\u5357\u3002\u5b78\u7fd2\u55ae\u5143\u96a8\u9644\u4ee3\u78bc\u793a\u4f8b\uff0c\u60a8\u53ef\u4ee5\u904b\u884c\u548c\u4fee\u6539\u3002\n- [Apache Beam \u5712\u5730](https://play.beam.apache.org/) \uff1a\u4e00\u500b\u4ea4\u4e92\u5f0f\u74b0\u5883\uff0c\u7528\u65bc\u8a66\u7528 Apache Beam \u8f49\u63db\u548c\u793a\u4f8b\uff0c\u800c\u7121\u9700\u5728\u60a8\u7684\u74b0\u5883\u4e2d\u5b89\u88dd Apache Beam\u3002\n\u5728 Apache Beam \u7db2\u7ad9\u4e0a\uff0c\u60a8\u9084\u53ef\u4ee5\u627e\u5230\u6709\u95dc\u5982\u4f55\u8a2d\u8a08\u3001\u5275\u5efa\u548c\u6e2c\u8a66\u6d41\u6c34\u7dda\u7684\u4fe1\u606f\uff1a\n- [\u8a2d\u8a08\u6d41\u6c34\u7dda](https://beam.apache.org/documentation/pipelines/design-your-pipeline/) \uff1a\u4ecb\u7d39\u77ad\u5982\u4f55\u78ba\u5b9a\u6d41\u6c34\u7dda\u7d50\u69cb\u3001\u5982\u4f55\u9078\u64c7\u8981\u61c9\u7528\u65bc\u6578\u64da\u7684\u8f49\u63db\uff0c\u4ee5\u53ca\u5982\u4f55\u78ba\u5b9a\u8f38\u5165\u548c\u8f38\u51fa\u65b9\u6cd5\u3002\n- [\u5275\u5efa\u6d41\u6c34\u7dda](https://beam.apache.org/documentation/pipelines/create-your-pipeline/) \uff1a\u4ecb\u7d39\u4e86\u4f7f\u7528 Apache Beam SDK \u4e2d\u7684\u985e\u7684\u6a5f\u5236\u4ee5\u53ca\u69cb\u5efa\u6d41\u6c34\u7dda\u6240\u9700\u7684\u5fc5\u8981\u6b65\u9a5f\u3002\n- [\u6e2c\u8a66\u6d41\u6c34\u7dda](https://beam.apache.org/documentation/pipelines/test-your-pipeline/) \uff1a\u4ecb\u7d39\u4e86\u6e2c\u8a66\u6d41\u6c34\u7dda\u7684\u6700\u4f73\u5be6\u8e10", "content": "\u3002", "guide": "Dataflow"}