{"title": "Apigee - Pod metrics annotations details", "url": "https://cloud.google.com/apigee/docs/api-platform/get-started/what-apigee", "abstract": "# Apigee - Pod metrics annotations details\nYou are currently viewing version 1.8 of the Apigee hybrid documentation. **This version is end of life.** You should upgrade to a newer version. For more information, see [Supported versions](/apigee/docs/hybrid/supported-platforms#supported-versions) .\n", "content": "## \n Overview\nApigee hybrid uses the industry-standard Prometheus add-on for metrics collection. All Apigee hybrid runtime plane applications expose an HTTP(s) endpoint that a [Prometheus](https://prometheus.io/) server can scrape. The Metrics are formatted in [OpenCensus](https://opencensus.io/introduction/) format.\nYou can use your own metrics collection and reporting service, keeping in mind that Apigee hybrid metrics are formatted in OpenCensus for scraping by a Prometheus server.\nThe following table lists port number and endpoint where hybrid exposes metrics for scraping for each runtime plane pods.\n| Apigee component name | Port number | Metrics endpoint |\n|:------------------------|--------------:|:-------------------|\n| Cassandra    |   7070 | /metrics   |\n| Connect Agent   |   7070 | /metrics   |\n| Mart     |   8843 | /v1/mart/metrics |\n| Redis     |   8001 | /stats/promethues |\n| Runtime     |   8843 | /v1/server/metrics |\n| Synchronizer   |   8843 | /v1/sync/metrics |\n| UDCA     |   7070 | /v1/server/metrics |\n| Watcher     |   8843 | /metricz   |\n### \n Example\nThe following example shows collecting metrics on the Runtime component from the command line:\n```\nkubectl -n apigee port-forward RUNTIME_POD_NAME 8843:8843\ncurl -k https://0:8843/v1/server/metrics?type=\"prometheus\"\n```", "guide": "Apigee"}