{"title": "Recommender - View logs", "url": "https://cloud.google.com/recommender/docs/viewing-logs", "abstract": "# Recommender - View logs\n# View logs\nRecommender logs record changes to recommendation and insight state.\n", "content": "## Permissions\nIdentity and Access Management permissions and roles determine which logs you can view and export.\nTo view Recommender logs, you must have one of the following IAM roles in the project that contains your logs:\n- One of the basic roles: **Project Owner** , **Project Editor** , or **Project Viewer** .\n- The Cloud Logging [Logs Viewer](/logging/docs/access-control#permissions_and_roles) role.\n- A [custom IAM role](/iam/docs/creating-custom-roles) with the`logging.logEntries.list`IAM permission.## Viewing logs\n### Recommendation Logs\nTo view recommendation action logs:\n- Go to the **Google Cloud Observability Logging > Logs** (Logs Explorer) page in the Google Cloud console: [Go to the Logs Explorer page](https://console.cloud.google.com/logs/query) \n- Select an existing Google Cloud project at the top of the page or create a new project.\n- In the first drop-down menu, select **Recommender** .\n- Expand a log entry to view the entry details. The following example shows a claimed recommendation.```\n{\u00a0insertId: \u00a0\"t51fxaa1\"\u00a0jsonPayload: {\u00a0 @type: \u00a0\"type.googleapis.com/google.cloud.recommender.logging.v1.ActionLog\"\u00a0 actor: \u00a0\"user@gmail.com\"\u00a0 recommendationName: \u00a0 \"projects/my-recommender-project/locations/global/recommenders/google.iam.policy.Recommender/recommendations/r1\"\u00a0 state: \u00a0\"CLAIMED\"\u00a0 stateMetadata: {\u00a0 \u00a0 my_metadata: \"Some metadata.\"\u00a0 }\u00a0}\u00a0logName: \u00a0\"projects/my-recommender-project/logs/recommender.googleapis.com%2Factions\"\u00a0receiveTimestamp: \u00a0\"2019-07-01T21:55:06.950795284Z\"\u00a0resource: {\u00a0 labels: {\u00a0 \u00a0location: \u00a0\"global\"\u00a0 \u00a0project_id: \u00a0\"my-recommender-project\"\u00a0 \u00a0recommender_id: \u00a0\"google.iam.policy.Recommender\"\u00a0 }\u00a0 type: \u00a0\"recommender\"\u00a0}\u00a0severity: \u00a0\"INFO\"\u00a0timestamp: \u00a0\"2019-07-01T21:55:06.529Z\"}\n```\n### Insight Logs\nTo view insight action logs:\n- Go to the **Google Cloud Observability Logging > Logs** (Logs Explorer) page in the Google Cloud console: [Go to the Logs Explorer page](https://console.cloud.google.com/logs/query) \n- Select an existing Google Cloud project at the top of the page or create a new project.\n- In the first drop-down menu, select **InsightType** .\n- Expand a log entry to view the entry details. The following example shows an accepted insight.```\n{\u00a0insertId: \u00a0\"t51fxaa1\"\u00a0jsonPayload: {\u00a0 @type: \u00a0\"type.googleapis.com/google.cloud.recommender.logging.v1.InsightActionLog\"\u00a0 actor: \u00a0\"user@gmail.com\"\u00a0 insight: \u00a0 \"projects/my-recommender-project/locations/global/insightTypes/google.iam.policy.Insight/insights/i1\"\u00a0 state: \u00a0\"ACCEPTED\"\u00a0 stateMetadata: {\u00a0 \u00a0 my_metadata: \"Some metadata.\"\u00a0 }\u00a0}\u00a0logName: \u00a0\"projects/my-recommender-project/logs/recommender.googleapis.com%2Factions\"\u00a0receiveTimestamp: \u00a0\"2019-07-01T21:55:06.950795284Z\"\u00a0resource: {\u00a0 labels: {\u00a0 \u00a0location: \u00a0\"global\"\u00a0 \u00a0project_id: \u00a0\"my-recommender-project\"\u00a0 \u00a0insight_type_id: \u00a0\"google.iam.policy.Recommender\"\u00a0 }\u00a0 type: \u00a0\"recommender_insight_type\"\u00a0}\u00a0severity: \u00a0\"INFO\"\u00a0timestamp: \u00a0\"2019-07-01T21:55:06.529Z\"}\n```", "guide": "Recommender"}